velikafkaclient/__init__.py
velikafkaclient/asyncconsumer.py
velikafkaclient/constants.py
velikafkaclient/consumer.py
velikafkaclient/decorators.py
velikafkaclient/eventregistration.py
velikafkaclient/exceptions.py
velikafkaclient/killer.py
velikafkaclient/producer.py
velikafkaclient/topicmanager.py
velikafkaclient/events/__init__.py
velikafkaclient/events/base.py
velikafkaclient/events/triptracker.py
velikafkaclient/topics/__init__.py
velikafkaclient/topics/topics.py
velikafkaclient/topics/triptracker.py
velikafkaclient-1.4.0.dist-info/METADATA
velikafkaclient-1.4.0.dist-info/WHEEL
velikafkaclient-1.4.0.dist-info/top_level.txt
velikafkaclient-1.4.0.dist-info/RECORD
