Metadata-Version: 2.4
Name: velikafkaclient
Version: 1.4.0
Summary: Veli Kafka Client
Author: Konstantine
Author-email: kdvalishvili@veli.store
Requires-Dist: confluent-kafka
Requires-Dist: pydantic
Requires-Dist: velilogger
Requires-Dist: aiokafka
Dynamic: author
Dynamic: author-email
Dynamic: description
Dynamic: description-content-type
Dynamic: requires-dist
Dynamic: summary
